[
  {
    "id": "app-1",
    "name": "Classic Bruschetta",
    "description": "Toasted bread with tomatoes, garlic, and fresh basil.",
    "basePrice": 8.00,
    "category": "Appetizers",
    "imageUrl": "https://images.unsplash.com/photo-1572695157366-5e585ab2b69f?w=800&q=80"
  },
  {
    "id": "sal-1",
    "name": "Caesar Salad",
    "description": "Crisp romaine, parmesan cheese, house croutons.",
    "basePrice": 10.00,
    "category": "Salads",
    "imageUrl": "https://images.unsplash.com/photo-1550304943-4f24f54ddde9?w=800&q=80"
  },
  {
    "id": "low-1",
    "name": "Keto Pizza Bowl",
    "description": "All your favorite pizza toppings baked in a bowl without the crust.",
    "basePrice": 12.00,
    "category": "Low Carb",
    "imageUrl": "https://images.unsplash.com/photo-1544982503-9f984c14501a?w=800&q=80"
  },
  {
    "id": "cyo-1",
    "name": "Create Your Own Pizza",
    "description": "Start with our classic cheese and add your favorite toppings.",
    "basePrice": 10.00,
    "category": "Create Your Own Pizza",
    "imageUrl": "https://images.unsplash.com/photo-1590947132387-155cc02f3212?w=800&q=80",
    "isCustomizable": true,
    "availableSizes": [
      { "label": "Small 10\"", "priceModifier": 0 },
      { "label": "Medium 12\"", "priceModifier": 3.00 },
      { "label": "Large 14\"", "priceModifier": 5.00 },
      { "label": "X-Large 16\"", "priceModifier": 7.00 }
    ],
    "availableCrusts": [
      { "label": "Regular", "priceModifier": 0 },
      { "label": "Thin", "priceModifier": 0 },
      { "label": "Stuffed", "priceModifier": 2.00 },
      { "label": "Gluten-Free", "priceModifier": 3.00 }
    ]
  },
  {
    "id": "clas-1",
    "name": "Classic Cheese",
    "description": "Simple, elegant, perfect.",
    "basePrice": 12.00,
    "category": "Classic Pizzas",
    "imageUrl": "https://images.unsplash.com/photo-1574071318508-1cdbab80d002?w=800&q=80"
  },
  {
    "id": "sig-1",
    "name": "The Works",
    "description": "Pepperoni, sausage, green peppers, onions, and mushrooms.",
    "basePrice": 18.00,
    "category": "Signature Pizzas",
    "imageUrl": "https://images.unsplash.com/photo-1513104890138-7c749659a591?w=800&q=80"
  },
  {
    "id": "des-1",
    "name": "Tiramisu",
    "description": "Espresso and mascarpone delight.",
    "basePrice": 6.00,
    "category": "Desserts",
    "imageUrl": "https://images.unsplash.com/photo-1571877227200-a0d98ea607e9?w=800&q=80"
  },
  {
    "id": "bev-1",
    "name": "Artisan Cola",
    "description": "Craft soda made with real cane sugar.",
    "basePrice": 3.00,
    "category": "Beverages",
    "imageUrl": "https://images.unsplash.com/photo-1622483767028-3f66f32aef97?w=800&q=80"
  },
  {
    "id": "pas-1",
    "name": "Fettuccine Alfredo",
    "description": "Creamy parmesan cheese sauce served over fettuccine pasta.",
    "basePrice": 14.00,
    "category": "Pastas",
    "imageUrl": "https://images.unsplash.com/photo-1645112411341-6c4fd023714a?w=800&q=80"
  },
  {
    "id": "cal-1",
    "name": "Meatball Calzone",
    "description": "Stuffed with meatballs, marinara, and lots of cheese.",
    "basePrice": 15.00,
    "category": "Calzones",
    "imageUrl": "https://images.unsplash.com/photo-1628840042765-356cda07504e?w=800&q=80"
  },
  {
    "id": "sub-1",
    "name": "Italian Deli Sub",
    "description": "Salami, pepperoni, ham, provolone, toasted hot.",
    "basePrice": 11.00,
    "category": "Hot Subs",
    "imageUrl": "https://images.unsplash.com/photo-1627054234033-02f82ba1f1b2?w=800&q=80"
  },
  {
    "id": "flat-1",
    "name": "Margherita Flatbread",
    "description": "Thin crispy crust topped with fresh mozzarella and basil.",
    "basePrice": 9.00,
    "category": "Flat Breads",
    "imageUrl": "https://images.unsplash.com/photo-1565299624946-b28f40a0ae38?w=800&q=80"
  },
  {
    "id": "spec-1",
    "name": "Truffle Mushroom",
    "description": "Wild mushrooms, truffle oil, white sauce.",
    "basePrice": 20.00,
    "category": "Specialty Pizzas",
    "imageUrl": "https://images.unsplash.com/photo-1513104890138-7c749659a591?w=800&q=80"
  }
]
